pipe_fp/__init__.py
pipe_fp/pipe.py
pipe_fp/type/TypeVar.py
pipe_fp/type/__init__.py
pipe_fp-2.0.0.dist-info/LICENSE
pipe_fp-2.0.0.dist-info/METADATA
pipe_fp-2.0.0.dist-info/WHEEL
pipe_fp-2.0.0.dist-info/RECORD
